{
    "map": {
        "mode": "Standard Battle",
        "name": "Murovanka"
    },
    "result": {
        "name": "Victory",
        "reason": "All vehicles destroyed",
        "winner": 2
    },
    "subject": {
        "name": "N0nz",
        "team": 2
    },
    "teams": [
        {
            "players": [
                {
                    "general_stats": {
                        "WN8": 1541,
                        "battles": 41211,
                        "winrate": 53.18
                    },
                    "name": "CoolDozer",
                    "performance": {
                        "assisted_dmg": 1030,
                        "damage_dealt": 4929,
                        "lifetime": 424,
                        "survived": false
                    },
                    "tank": {
                        "category": "Medium Tank",
                        "name": "Centurion Action X",
                        "nation": "United Kingdom",
                        "tier": 10
                    },
                    "tank_stats": {
                        "WN8": 1639,
                        "battles": 408,
                        "damage": 1891,
                        "winrate": 49.02
                    }
                },
                {
                    "general_stats": {
                        "WN8": 516,
                        "battles": 13419,
                        "winrate": 46.41
                    },
                    "name": "abadon_82",
                    "performance": {
                        "assisted_dmg": 51,
                        "damage_dealt": 589,
                        "lifetime": 124,
                        "survived": false
                    },
                    "tank": {
                        "category": "Medium Tank",
                        "name": "Bat.-Châtillon 25 t AP",
                        "nation": "France",
                        "tier": 9
                    },
                    "tank_stats": {
                        "WN8": 513,
                        "battles": 291,
                        "damage": 736,
                        "winrate": 43.64
                    }
                },
                {
                    "general_stats": {
                        "WN8": 1009,
                        "battles": 29164,
                        "winrate": 49.22
                    },
                    "name": "mainrj",
                    "performance": {
                        "assisted_dmg": 224,
                        "damage_dealt": 1019,
                        "lifetime": 243,
                        "survived": false
                    },
                    "tank": {
                        "category": "SPG",
                        "name": "T92 HMC",
                        "nation": "USA",
                        "tier": 10
                    },
                    "tank_stats": {
                        "WN8": 1264,
                        "battles": 726,
                        "damage": 1445,
                        "winrate": 47.66
                    }
                },
                {
                    "general_stats": {
                        "WN8": 1055,
                        "battles": 54863,
                        "winrate": 50.28
                    },
                    "name": "road_iron",
                    "performance": {
                        "assisted_dmg": 2373,
                        "damage_dealt": 394,
                        "lifetime": 227,
                        "survived": false
                    },
                    "tank": {
                        "category": "Medium Tank",
                        "name": "Leopard Prototyp A",
                        "nation": "Germany",
                        "tier": 9
                    },
                    "tank_stats": {
                        "WN8": 401,
                        "battles": 296,
                        "damage": 709,
                        "winrate": 39.86
                    }
                },
                {
                    "general_stats": {
                        "WN8": 2572,
                        "battles": 19337,
                        "winrate": 58.11
                    },
                    "name": "_D357R0Y3R_",
                    "performance": {
                        "assisted_dmg": 0,
                        "damage_dealt": 2280,
                        "lifetime": 295,
                        "survived": false
                    },
                    "tank": {
                        "category": "Tank Destroyer",
                        "name": "T110E4",
                        "nation": "USA",
                        "tier": 10
                    },
                    "tank_stats": {
                        "WN8": 2377,
                        "battles": 27,
                        "damage": 3070,
                        "winrate": 66.67
                    }
                },
                {
                    "general_stats": {
                        "WN8": 1409,
                        "battles": 14616,
                        "winrate": 50.55
                    },
                    "name": "GetYourTanksssssOn",
                    "performance": {
                        "assisted_dmg": 1061,
                        "damage_dealt": 1589,
                        "lifetime": 180,
                        "survived": false
                    },
                    "tank": {
                        "category": "Light Tank",
                        "name": "XM551 Sheridan",
                        "nation": "USA",
                        "tier": 10
                    },
                    "tank_stats": {
                        "WN8": 1197,
                        "battles": 40,
                        "damage": 1325,
                        "winrate": 40.0
                    }
                },
                {
                    "general_stats": {
                        "WN8": 836,
                        "battles": 36168,
                        "winrate": 46.99
                    },
                    "name": "DOZER5050",
                    "performance": {
                        "assisted_dmg": 865,
                        "damage_dealt": 902,
                        "lifetime": 190,
                        "survived": false
                    },
                    "tank": {
                        "category": "Heavy Tank",
                        "name": "Conqueror",
                        "nation": "United Kingdom",
                        "tier": 9
                    },
                    "tank_stats": {
                        "WN8": 452,
                        "battles": 50,
                        "damage": 764,
                        "winrate": 44.0
                    }
                },
                {
                    "general_stats": {
                        "WN8": 1396,
                        "battles": 27194,
                        "winrate": 50.63
                    },
                    "name": "defects",
                    "performance": {
                        "assisted_dmg": 0,
                        "damage_dealt": 2929,
                        "lifetime": 333,
                        "survived": false
                    },
                    "tank": {
                        "category": "Tank Destroyer",
                        "name": "FV215b (183)",
                        "nation": "United Kingdom",
                        "tier": 10
                    },
                    "tank_stats": {
                        "WN8": 986,
                        "battles": 152,
                        "damage": 1501,
                        "winrate": 48.68
                    }
                },
                {
                    "general_stats": {
                        "WN8": 1445,
                        "battles": 11353,
                        "winrate": 50.72
                    },
                    "name": "Stormblitzwar",
                    "performance": {
                        "assisted_dmg": 575,
                        "damage_dealt": 1530,
                        "lifetime": 206,
                        "survived": false
                    },
                    "tank": {
                        "category": "Tank Destroyer",
                        "name": "Jagdtiger",
                        "nation": "Germany",
                        "tier": 9
                    },
                    "tank_stats": {
                        "WN8": 927,
                        "battles": 50,
                        "damage": 1317,
                        "winrate": 40.0
                    }
                },
                {
                    "general_stats": {
                        "WN8": 1363,
                        "battles": 23033,
                        "winrate": 51.08
                    },
                    "name": "Acer_LTU",
                    "performance": {
                        "assisted_dmg": 0,
                        "damage_dealt": 968,
                        "lifetime": 131,
                        "survived": false
                    },
                    "tank": {
                        "category": "Medium Tank",
                        "name": "Škoda T 50",
                        "nation": "Czechoslovakia",
                        "tier": 9
                    },
                    "tank_stats": {
                        "WN8": 1823,
                        "battles": 157,
                        "damage": 1960,
                        "winrate": 53.5
                    }
                },
                {
                    "general_stats": {
                        "WN8": 1904,
                        "battles": 25286,
                        "winrate": 53.03
                    },
                    "name": "Jrpink13",
                    "performance": {
                        "assisted_dmg": 1783,
                        "damage_dealt": 969,
                        "lifetime": 238,
                        "survived": false
                    },
                    "tank": {
                        "category": "Heavy Tank",
                        "name": "VK 45.02 (P) Ausf. B",
                        "nation": "Germany",
                        "tier": 9
                    },
                    "tank_stats": {
                        "WN8": 2183,
                        "battles": 543,
                        "damage": 1946,
                        "winrate": 50.83
                    }
                },
                {
                    "general_stats": {
                        "WN8": 796,
                        "battles": 29710,
                        "winrate": 47.57
                    },
                    "name": "bosanac1970",
                    "performance": {
                        "assisted_dmg": 572,
                        "damage_dealt": 707,
                        "lifetime": 142,
                        "survived": false
                    },
                    "tank": {
                        "category": "Medium Tank",
                        "name": "Bat.-Châtillon 25 t AP",
                        "nation": "France",
                        "tier": 9
                    },
                    "tank_stats": {
                        "WN8": 963,
                        "battles": 395,
                        "damage": 1135,
                        "winrate": 44.56
                    }
                },
                {
                    "general_stats": {
                        "WN8": 858,
                        "battles": 42648,
                        "winrate": 47.58
                    },
                    "name": "buzz1947",
                    "performance": {
                        "assisted_dmg": 79,
                        "damage_dealt": 0,
                        "lifetime": 139,
                        "survived": false
                    },
                    "tank": {
                        "category": "Light Tank",
                        "name": "Spähpanzer Ru 251",
                        "nation": "Germany",
                        "tier": 9
                    },
                    "tank_stats": {
                        "WN8": 615,
                        "battles": 1426,
                        "damage": 534,
                        "winrate": 46.42
                    }
                },
                {
                    "general_stats": {
                        "WN8": 1300,
                        "battles": 16930,
                        "winrate": 52.51
                    },
                    "name": "turbocarz",
                    "performance": {
                        "assisted_dmg": 0,
                        "damage_dealt": 2345,
                        "lifetime": 266,
                        "survived": false
                    },
                    "tank": {
                        "category": "SPG",
                        "name": "M53/M55",
                        "nation": "USA",
                        "tier": 9
                    },
                    "tank_stats": {
                        "WN8": 1833,
                        "battles": 176,
                        "damage": 1774,
                        "winrate": 50.57
                    }
                },
                {
                    "general_stats": {
                        "WN8": 1081,
                        "battles": 34761,
                        "winrate": 49.26
                    },
                    "name": "tha_masta",
                    "performance": {
                        "assisted_dmg": 490,
                        "damage_dealt": 1717,
                        "lifetime": 443,
                        "survived": false
                    },
                    "tank": {
                        "category": "Tank Destroyer",
                        "name": "Object 704",
                        "nation": "USSR",
                        "tier": 9
                    },
                    "tank_stats": {
                        "WN8": 1204,
                        "battles": 647,
                        "damage": 1580,
                        "winrate": 51.16
                    }
                }
            ],
            "spawn": "A",
            "team_id": 1
        },
        {
            "players": [
                {
                    "general_stats": {
                        "WN8": 1266,
                        "battles": 20284,
                        "winrate": 50.04
                    },
                    "name": "CamuMahubah",
                    "performance": {
                        "assisted_dmg": 952,
                        "damage_dealt": 895,
                        "lifetime": 448,
                        "survived": true
                    },
                    "tank": {
                        "category": "Tank Destroyer",
                        "name": "T30",
                        "nation": "USA",
                        "tier": 9
                    },
                    "tank_stats": {
                        "WN8": 1346,
                        "battles": 127,
                        "damage": 1654,
                        "winrate": 50.39
                    }
                },
                {
                    "general_stats": {
                        "WN8": 452,
                        "battles": 8250,
                        "winrate": 45.62
                    },
                    "name": "aerorack",
                    "performance": {
                        "assisted_dmg": 59,
                        "damage_dealt": 897,
                        "lifetime": 230,
                        "survived": false
                    },
                    "tank": {
                        "category": "Tank Destroyer",
                        "name": "Jagdtiger",
                        "nation": "Germany",
                        "tier": 9
                    },
                    "tank_stats": {
                        "WN8": 664,
                        "battles": 94,
                        "damage": 1053,
                        "winrate": 45.74
                    }
                },
                {
                    "general_stats": {
                        "WN8": 1762,
                        "battles": 15067,
                        "winrate": 53.34
                    },
                    "name": "Sinkface",
                    "performance": {
                        "assisted_dmg": 705,
                        "damage_dealt": 3195,
                        "lifetime": 448,
                        "survived": true
                    },
                    "tank": {
                        "category": "Heavy Tank",
                        "name": "Mäuschen",
                        "nation": "Germany",
                        "tier": 9
                    },
                    "tank_stats": {
                        "WN8": 2081,
                        "battles": 116,
                        "damage": 2097,
                        "winrate": 65.52
                    }
                },
                {
                    "general_stats": {
                        "WN8": 559,
                        "battles": 40061,
                        "winrate": 46.9
                    },
                    "name": "Sgt_WarDaddy",
                    "performance": {
                        "assisted_dmg": 1155,
                        "damage_dealt": 470,
                        "lifetime": 270,
                        "survived": false
                    },
                    "tank": {
                        "category": "SPG",
                        "name": "Bat.-Châtillon 155 58",
                        "nation": "France",
                        "tier": 10
                    },
                    "tank_stats": {
                        "WN8": 636,
                        "battles": 50,
                        "damage": 971,
                        "winrate": 46.0
                    }
                },
                {
                    "general_stats": {
                        "WN8": 2277,
                        "battles": 15098,
                        "winrate": 55.74
                    },
                    "name": "jimbo808",
                    "performance": {
                        "assisted_dmg": 0,
                        "damage_dealt": 0,
                        "lifetime": 135,
                        "survived": false
                    },
                    "tank": {
                        "category": "Light Tank",
                        "name": "AMX 13 105",
                        "nation": "France",
                        "tier": 10
                    },
                    "tank_stats": {
                        "WN8": 2004,
                        "battles": 139,
                        "damage": 1823,
                        "winrate": 51.8
                    }
                },
                {
                    "general_stats": {
                        "WN8": 1355,
                        "battles": 36727,
                        "winrate": 48.2
                    },
                    "name": "fastjam",
                    "performance": {
                        "assisted_dmg": 451,
                        "damage_dealt": 2880,
                        "lifetime": 288,
                        "survived": false
                    },
                    "tank": {
                        "category": "Tank Destroyer",
                        "name": "Grille 15",
                        "nation": "Germany",
                        "tier": 10
                    },
                    "tank_stats": {
                        "WN8": 1305,
                        "battles": 7111,
                        "damage": 1869,
                        "winrate": 47.49
                    }
                },
                {
                    "general_stats": {
                        "WN8": 1209,
                        "battles": 6789,
                        "winrate": 49.23
                    },
                    "name": "therabbilope",
                    "performance": {
                        "assisted_dmg": 672,
                        "damage_dealt": 271,
                        "lifetime": 141,
                        "survived": false
                    },
                    "tank": {
                        "category": "Medium Tank",
                        "name": "Bat.-Châtillon 25 t AP",
                        "nation": "France",
                        "tier": 9
                    },
                    "tank_stats": {
                        "WN8": 1851,
                        "battles": 101,
                        "damage": 1678,
                        "winrate": 50.5
                    }
                },
                {
                    "general_stats": {
                        "WN8": 580,
                        "battles": 18115,
                        "winrate": 47.5
                    },
                    "name": "meatisking",
                    "performance": {
                        "assisted_dmg": 562,
                        "damage_dealt": 1134,
                        "lifetime": 131,
                        "survived": false
                    },
                    "tank": {
                        "category": "Medium Tank",
                        "name": "Centurion Mk. 7/1",
                        "nation": "United Kingdom",
                        "tier": 9
                    },
                    "tank_stats": {
                        "WN8": 636,
                        "battles": 363,
                        "damage": 888,
                        "winrate": 43.25
                    }
                },
                {
                    "general_stats": {
                        "WN8": 1306,
                        "battles": 22246,
                        "winrate": 51.11
                    },
                    "name": "N0nz",
                    "performance": {
                        "assisted_dmg": 238,
                        "damage_dealt": 1005,
                        "lifetime": 448,
                        "survived": true
                    },
                    "tank": {
                        "category": "Heavy Tank",
                        "name": "E 100",
                        "nation": "Germany",
                        "tier": 10
                    },
                    "tank_stats": {
                        "WN8": 528,
                        "battles": 2,
                        "damage": 894,
                        "winrate": 50.0
                    }
                },
                {
                    "general_stats": {
                        "WN8": 1162,
                        "battles": 8404,
                        "winrate": 47.54
                    },
                    "name": "MonsterSlayer230",
                    "performance": {
                        "assisted_dmg": 1242,
                        "damage_dealt": 4256,
                        "lifetime": 448,
                        "survived": true
                    },
                    "tank": {
                        "category": "Medium Tank",
                        "name": "Bat.-Châtillon 25 t AP",
                        "nation": "France",
                        "tier": 9
                    },
                    "tank_stats": {
                        "WN8": 1880,
                        "battles": 176,
                        "damage": 1704,
                        "winrate": 52.27
                    }
                },
                {
                    "general_stats": {
                        "WN8": 1633,
                        "battles": 20626,
                        "winrate": 52.06
                    },
                    "name": "ForgottenSoups",
                    "performance": {
                        "assisted_dmg": 0,
                        "damage_dealt": 2876,
                        "lifetime": 407,
                        "survived": false
                    },
                    "tank": {
                        "category": "Medium Tank",
                        "name": "E 50",
                        "nation": "Germany",
                        "tier": 9
                    },
                    "tank_stats": {
                        "WN8": 2405,
                        "battles": 286,
                        "damage": 2155,
                        "winrate": 50.7
                    }
                },
                {
                    "general_stats": {
                        "WN8": 1045,
                        "battles": 21894,
                        "winrate": 48.83
                    },
                    "name": "allamerican37",
                    "performance": {
                        "assisted_dmg": 101,
                        "damage_dealt": 2999,
                        "lifetime": 336,
                        "survived": false
                    },
                    "tank": {
                        "category": "Tank Destroyer",
                        "name": "FV217 Badger",
                        "nation": "United Kingdom",
                        "tier": 10
                    },
                    "tank_stats": {
                        "WN8": 1321,
                        "battles": 5,
                        "damage": 2040,
                        "winrate": 60.0
                    }
                },
                {
                    "general_stats": {
                        "WN8": 1399,
                        "battles": 50041,
                        "winrate": 50.13
                    },
                    "name": "minivq",
                    "performance": {
                        "assisted_dmg": 1532,
                        "damage_dealt": 232,
                        "lifetime": 93,
                        "survived": false
                    },
                    "tank": {
                        "category": "Light Tank",
                        "name": "WZ-132A",
                        "nation": "China",
                        "tier": 9
                    },
                    "tank_stats": {
                        "WN8": 1466,
                        "battles": 47,
                        "damage": 1039,
                        "winrate": 57.45
                    }
                },
                {
                    "general_stats": {
                        "WN8": 1042,
                        "battles": 34285,
                        "winrate": 49.25
                    },
                    "name": "trueblue_1",
                    "performance": {
                        "assisted_dmg": 139,
                        "damage_dealt": 869,
                        "lifetime": 259,
                        "survived": false
                    },
                    "tank": {
                        "category": "SPG",
                        "name": "FV3805",
                        "nation": "United Kingdom",
                        "tier": 9
                    },
                    "tank_stats": {
                        "WN8": 706,
                        "battles": 116,
                        "damage": 914,
                        "winrate": 44.83
                    }
                },
                {
                    "general_stats": {
                        "WN8": 2386,
                        "battles": 37054,
                        "winrate": 55.44
                    },
                    "name": "bletsas",
                    "performance": {
                        "assisted_dmg": 679,
                        "damage_dealt": 2066,
                        "lifetime": 134,
                        "survived": false
                    },
                    "tank": {
                        "category": "Medium Tank",
                        "name": "AMX 30 1er prototype",
                        "nation": "France",
                        "tier": 9
                    },
                    "tank_stats": {
                        "WN8": 2918,
                        "battles": 278,
                        "damage": 2316,
                        "winrate": 65.47
                    }
                }
            ],
            "spawn": "B",
            "team_id": 2
        }
    ]
}